target_postgres/__init__.py
target_postgres/db_sync.py
target_postgres-1.1.3.dist-info/METADATA
target_postgres-1.1.3.dist-info/RECORD
target_postgres-1.1.3.dist-info/WHEEL
target_postgres-1.1.3.dist-info/entry_points.txt
target_postgres-1.1.3.dist-info/top_level.txt
