Metadata-Version: 1.1
Name: target-postgres
Version: 1.1.3
Summary: Singer.io target for Postgres
Home-page: https://statsbot.co
Author: Statsbot
Author-email: UNKNOWN
License: UNKNOWN
Platform: UNKNOWN
Classifier: Programming Language :: Python :: 3 :: Only
